ssh_run-3.1.0.dist-info/WHEEL
ssh_run-3.1.0.dist-info/RECORD
ssh_run-3.1.0.dist-info/DESCRIPTION.rst
ssh_run-3.1.0.dist-info/metadata.json
ssh_run-3.1.0.dist-info/entry_points.txt
ssh_run-3.1.0.dist-info/top_level.txt
ssh_run-3.1.0.dist-info/METADATA
ssh_run/__main__.py
ssh_run/ssh.py
ssh_run/run.py
ssh_run/runner.py
ssh_run/cli.py
ssh_run/__init__.py
