Metadata-Version: 2.0
Name: ssh-run
Version: 3.1.0
Summary: A tool for running commands on remote servers
Home-page: https://github.com/borntyping/ssh-run
Author: Sam Clements
Author-email: sam@borntyping.co.uk
License: MIT
Platform: UNKNOWN
Classifier: Development Status :: 3 - Alpha
Classifier: Environment :: Console
Classifier: License :: OSI Approved
Classifier: License :: OSI Approved :: MIT License
Classifier: Operating System :: Unix
Classifier: Programming Language :: Python
Classifier: Programming Language :: Python :: 3
Classifier: Topic :: Software Development :: Build Tools
Classifier: Topic :: System :: Systems Administration
Classifier: Topic :: Utilities
Requires-Dist: click
Requires-Dist: keyring
Requires-Dist: pexpect
Requires-Dist: termcolor
